TensorflowJiqiXuexiMijiZhongwenDierBanChuyiFix1/README.md
TensorflowJiqiXuexiMijiZhongwenDierBanChuyiFix1/__init__.py
TensorflowJiqiXuexiMijiZhongwenDierBanChuyiFix1/__main__.py
TensorflowJiqiXuexiMijiZhongwenDierBanChuyiFix1/file.epub
TensorflowJiqiXuexiMijiZhongwenDierBanChuyiFix1/index.html
TensorflowJiqiXuexiMijiZhongwenDierBanChuyiFix1/css/__init__.py
TensorflowJiqiXuexiMijiZhongwenDierBanChuyiFix1/css/annotations.css
TensorflowJiqiXuexiMijiZhongwenDierBanChuyiFix1/css/main.css
TensorflowJiqiXuexiMijiZhongwenDierBanChuyiFix1/css/normalize.css
TensorflowJiqiXuexiMijiZhongwenDierBanChuyiFix1/css/popup.css
TensorflowJiqiXuexiMijiZhongwenDierBanChuyiFix1/font/__init__.py
TensorflowJiqiXuexiMijiZhongwenDierBanChuyiFix1/font/fontello.eot
TensorflowJiqiXuexiMijiZhongwenDierBanChuyiFix1/font/fontello.svg
TensorflowJiqiXuexiMijiZhongwenDierBanChuyiFix1/font/fontello.ttf
TensorflowJiqiXuexiMijiZhongwenDierBanChuyiFix1/font/fontello.woff
TensorflowJiqiXuexiMijiZhongwenDierBanChuyiFix1/img/__init__.py
TensorflowJiqiXuexiMijiZhongwenDierBanChuyiFix1/img/annotator-glyph-sprite.png
TensorflowJiqiXuexiMijiZhongwenDierBanChuyiFix1/img/annotator-icon-sprite.png
TensorflowJiqiXuexiMijiZhongwenDierBanChuyiFix1/img/apple-touch-icon.png
TensorflowJiqiXuexiMijiZhongwenDierBanChuyiFix1/img/cancelfullscreen.png
TensorflowJiqiXuexiMijiZhongwenDierBanChuyiFix1/img/close.png
TensorflowJiqiXuexiMijiZhongwenDierBanChuyiFix1/img/fullscreen.png
TensorflowJiqiXuexiMijiZhongwenDierBanChuyiFix1/img/loader.gif
TensorflowJiqiXuexiMijiZhongwenDierBanChuyiFix1/img/menu-icon.png
TensorflowJiqiXuexiMijiZhongwenDierBanChuyiFix1/img/save.png
TensorflowJiqiXuexiMijiZhongwenDierBanChuyiFix1/img/saved.png
TensorflowJiqiXuexiMijiZhongwenDierBanChuyiFix1/img/settings-s.png
TensorflowJiqiXuexiMijiZhongwenDierBanChuyiFix1/img/settings.png
TensorflowJiqiXuexiMijiZhongwenDierBanChuyiFix1/img/star.png
TensorflowJiqiXuexiMijiZhongwenDierBanChuyiFix1/js/__init__.py
tensorflow_jiqi_xuexi_miji_zhongwen_dier_ban_chuyi_fix1-2025.3.24.1.dist-info/METADATA
tensorflow_jiqi_xuexi_miji_zhongwen_dier_ban_chuyi_fix1-2025.3.24.1.dist-info/WHEEL
tensorflow_jiqi_xuexi_miji_zhongwen_dier_ban_chuyi_fix1-2025.3.24.1.dist-info/entry_points.txt
tensorflow_jiqi_xuexi_miji_zhongwen_dier_ban_chuyi_fix1-2025.3.24.1.dist-info/top_level.txt
tensorflow_jiqi_xuexi_miji_zhongwen_dier_ban_chuyi_fix1-2025.3.24.1.dist-info/RECORD
